{"title":"DSM7 vhost","link":"https://www.llun.me/posts/dev/2021-08-08-DSM7-vhost/","date":1628380800000,"content":"\n      \n        <p>อัพเกรด DSM7 มาได้ซักพักแต่พึ่งได้มาลองแก้ vhost เพราะจะเล่น Grafana แล้วพบว่า Synology<br />\nเปลี่ยน structure nginx config จากเดิมอยู่ที่</p>\n<pre><code>/etc/nginx/app.d/server.webstation-vhost.conf\n</code></pre>\n<p>ย้ายมาอยู่ที่</p>\n<pre><code>/etc/nginx/sites-enabled/server.webstation-vhost.conf\n</code></pre>\n<p>ถ้าไม่เล่น docker จะไม่ต้องเข้ามาแก้ไฟล์พวกนี้ตรงๆ เพื่อ reverse proxy เลยแต่จริงๆ Synology<br />\nควรเพิ่ม Reverse proxy option ลงไปใน Web station ได้แล้วจะได้ไม่ต้องมาแก้อะไรแบบนี้เอง</p>\n<figure><a href=\"https://www.llun.me/posts/dev/2021-08-08-DSM7-vhost/vhost.png\"><img src=\"https://www.llun.me/posts/dev/2021-08-08-DSM7-vhost/vhost.png\" /></a><figcaption>Webstation vhost settings ทำได้แค่ static files หรือ PHP</figcaption></figure>\n\n        <p>\n          <a href=\"mailto:comment@llun.me?subject=Common on post https://www.llun.me/posts/dev/2021-08-08-DSM7-vhost/\">Send a comment</a>\n        </p>\n      \n    ","author":"Maythee Anegboonlap","siteTitle":"@llun story","siteHash":"e492a4c5a091b6624e5872d8d003bc73eb1166cc8f88db58c44e1f8dfb9c7252","entryHash":"8c67baac9c4c27d83bd4a574e1c77ddada1bd4c96d8078a1e0fc41b4dd417ba9","category":"Me"}